{"Blocks":[{"Id":"2","Type":"fromwebsocket","Rule":{"url":"ws://wikimon.hatnote.com:80/en/"},"Position":{"X":100,"Y":39}},{"Id":"5","Type":"filter","Rule":{"Filter":"(.is_minor == false) && (.is_bot == false)"},"Position":{"X":171,"Y":139}},{"Id":"41","Type":"histogram","Rule":{"Path":".user","Window":"1h0m0s"},"Position":{"X":754,"Y":582}},{"Id":"27","Type":"tofile","Rule":{"Filename":"/home/ubuntu/wiki.json"},"Position":{"X":672,"Y":677}},{"Id":"33","Type":"mask","Rule":{"Mask":{"summary":{},"user":{}}},"Position":{"X":433,"Y":427}},{"Id":"18","Type":"filter","Rule":{"Filter":".is_anon == false"},"Position":{"X":267,"Y":228}},{"Id":"38","Type":"filter","Rule":{"Filter":".summary != null"},"Position":{"X":335,"Y":330}}],"Connections":[{"Id":"43","FromId":"33","ToId":"27","ToRoute":"in"},{"Id":"6","FromId":"2","ToId":"5","ToRoute":"in"},{"Id":"20","FromId":"5","ToId":"18","ToRoute":"in"},{"Id":"44","FromId":"18","ToId":"38","ToRoute":"in"},{"Id":"40","FromId":"38","ToId":"33","ToRoute":"in"},{"Id":"42","FromId":"33","ToId":"41","ToRoute":"in"}]}